glade/__init__.py
glade-0.0.1.dist-info/METADATA
glade-0.0.1.dist-info/WHEEL
glade-0.0.1.dist-info/RECORD
